endoreg_db/__init__.py
endoreg_db/_version.py
endoreg_db/admin.py
endoreg_db/api_urls.py
endoreg_db/apps.py
endoreg_db/exceptions.py
endoreg_db/logger_conf.py
endoreg_db/root_urls.py
endoreg_db/urls.py
endoreg_db/versioning.md
endoreg_db/api/serializers/finding_descriptions.py
endoreg_db/api/views/finding_descriptions.py
endoreg_db/assets/dummy_model.ckpt
endoreg_db/authz/auth.py
endoreg_db/authz/backends.py
endoreg_db/authz/middleware.py
endoreg_db/authz/permissions.py
endoreg_db/authz/policy.py
endoreg_db/authz/settings.py
endoreg_db/authz/views_auth.py
endoreg_db/authz/management/commands/list_routes.py
endoreg_db/codemods/readme.md
endoreg_db/codemods/rename_datetime_fields.py
endoreg_db/config/__init__.py
endoreg_db/config/env.py
endoreg_db/config/settings/__init__.py
endoreg_db/config/settings/base.py
endoreg_db/config/settings/case_gen.py
endoreg_db/config/settings/dev.py
endoreg_db/config/settings/keycloak.py
endoreg_db/config/settings/prod.py
endoreg_db/config/settings/test.py
endoreg_db/data/__init__.py
endoreg_db/data/db_summary.csv
endoreg_db/data/db_summary.xlsx
endoreg_db/data/setup_config.yaml
endoreg_db/data/ai_model/data.yaml
endoreg_db/data/ai_model_label/label/data.yaml
endoreg_db/data/ai_model_label/label/polyp_classification.yaml
endoreg_db/data/ai_model_label/label-set/data.yaml
endoreg_db/data/ai_model_label/label-set/polyp_classifications.yaml
endoreg_db/data/ai_model_label/label-type/data.yaml
endoreg_db/data/ai_model_meta/default_multilabel_classification.yaml
endoreg_db/data/ai_model_type/data.yaml
endoreg_db/data/ai_model_video_segmentation_label/base_segmentation.yaml
endoreg_db/data/ai_model_video_segmentation_labelset/data.yaml
endoreg_db/data/case_template/rule/00_patient_lab_sample_add_default_value.yaml
endoreg_db/data/case_template/rule/01_patient-set-age.yaml
endoreg_db/data/case_template/rule/01_patient-set-gender.yaml
endoreg_db/data/case_template/rule/11_create_patient_lab_sample.yaml
endoreg_db-0.8.9.24.dist-info/METADATA
endoreg_db-0.8.9.24.dist-info/WHEEL
endoreg_db-0.8.9.24.dist-info/licenses/LICENSE
endoreg_db-0.8.9.24.dist-info/RECORD
