Metadata-Version: 2.4
Name: endoreg-db
Version: 0.8.9.24
Summary: EndoReg Db Django App
Project-URL: Homepage, https://info.coloreg.de
Project-URL: Repository, https://github.com/wg-lux/endoreg-db
Author: Max Hild, Hamza Zahid, Peter Kowalczyk
Author-email: "Thomas J. Lux" <lux_t1@ukw.de>
Maintainer: Max Hild, Hamza Zahid, Peter Kowalczyk
Maintainer-email: "Thomas J. Lux" <lux_t1@ukw.de>
License-File: LICENSE
Classifier: Development Status :: 3 - Alpha
Classifier: Programming Language :: Python :: 3.12
Classifier: Topic :: Scientific/Engineering :: Medical Science Apps.
Requires-Python: <3.13,>=3.12
Requires-Dist: agl-report-reader>=0.4.0
Requires-Dist: build>=1.3.0
Requires-Dist: celery>=5.5.3
Requires-Dist: cryptography>=44.0.2
Requires-Dist: decord==0.6.0
Requires-Dist: django-bootstrap5>=25.2
Requires-Dist: django-cors-headers>=4.8.0
Requires-Dist: django-extensions>=3.2.3
Requires-Dist: django-filter>=25.1
Requires-Dist: django-stubs>=5.2.8
Requires-Dist: django>=5.2.4
Requires-Dist: djangorestframework-stubs>=3.16.6
Requires-Dist: djangorestframework>=3.16.1
Requires-Dist: dotenv>=0.9.9
Requires-Dist: faker>=37.6.0
Requires-Dist: flake8>=7.3.0
Requires-Dist: googlemaps>=4.10.0
Requires-Dist: gunicorn>=23.0.0
Requires-Dist: icecream>=2.1.4
Requires-Dist: librosa==0.11.0
Requires-Dist: llvmlite>=0.44.0
Requires-Dist: lx-anonymizer[llm,ocr]
Requires-Dist: moviepy==2.2.1
Requires-Dist: mozilla-django-oidc>=4.0.1
Requires-Dist: mypy>=1.16.0
Requires-Dist: numpy>=2.2.3
Requires-Dist: oauth2-proxy>=1.0.11
Requires-Dist: opencv-python>=4.11.0.86
Requires-Dist: openpyxl>=3.1.5
Requires-Dist: optimum==1.26.1
Requires-Dist: pandas>=2.2.3
Requires-Dist: pillow>=11.3.0
Requires-Dist: pip>=25.2
Requires-Dist: pre-commit>=4.5.1
Requires-Dist: pydantic>=2.10.6
Requires-Dist: pyjwt>=2.10.1
Requires-Dist: pytesseract>=0.3.13
Requires-Dist: pytest-cov>=6.1.1
Requires-Dist: pytest-django>=4.11.1
Requires-Dist: pytest-env>=1.1.5
Requires-Dist: pytest>=8.3.5
Requires-Dist: python-ffmpeg>=2.0.12
Requires-Dist: python-jose[cryptography]>=3.5.0
Requires-Dist: python-magic>=0.4.27
Requires-Dist: pytorch-lightning>=2.5.1
Requires-Dist: pyyaml>=6.0.2
Requires-Dist: regex>=2024.11.6
Requires-Dist: requests>=2.32.3
Requires-Dist: ruff>=0.14.0
Requires-Dist: safetensors>=0.4.5
Requires-Dist: scikit-learn>=1.5.2
Requires-Dist: scipy>=1.16.1
Requires-Dist: soundfile==0.12.1
Requires-Dist: sphinx-rtd-theme>=3.0.2
Requires-Dist: sphinx>=8.2.3
Requires-Dist: tesseract>=0.1.3
Requires-Dist: torch==2.5.1
Requires-Dist: torchaudio==2.5.1
Requires-Dist: torchvision==0.20.1
Requires-Dist: tqdm>=4.67.0
Requires-Dist: transformers==4.44.2
Requires-Dist: twine>=6.2.0
Requires-Dist: types-django-filter>=25.2.0.20251010
Requires-Dist: types-pyyaml>=6.0.12.20250915
Requires-Dist: types-requests>=2.32.4.20250913
Requires-Dist: types-tqdm>=4.67.0.20250809
Requires-Dist: urllib3>=2.2.3
Requires-Dist: vector-quantize-pytorch==1.18.5
Requires-Dist: vocos==0.1.0
Requires-Dist: whitenoise>=6.10.0
Provides-Extra: dev
Requires-Dist: black; extra == 'dev'
Requires-Dist: mypy; extra == 'dev'
Requires-Dist: pytest; extra == 'dev'
Requires-Dist: ruff; extra == 'dev'
Provides-Extra: docs
Requires-Dist: furo>=2025.9.25; extra == 'docs'
Requires-Dist: linkify-it-py>=2.0.3; extra == 'docs'
Requires-Dist: myst-parser>=4.0.1; extra == 'docs'
Requires-Dist: sphinx-autodoc-typehints>=3.5.2; extra == 'docs'
Requires-Dist: sphinx-copybutton>=0.5.2; extra == 'docs'
Requires-Dist: sphinx<9.0,>=8.2.3; extra == 'docs'
